setup.py
lxdspawner/__init__.py
lxdspawner/spawner.py
lxdspawner/utils.py
lxdspawner.egg-info/PKG-INFO
lxdspawner.egg-info/SOURCES.txt
lxdspawner.egg-info/dependency_links.txt
lxdspawner.egg-info/requires.txt
lxdspawner.egg-info/top_level.txt