Metadata-Version: 1.1
Name: lxdspawner
Version: 0.1
Summary: JupyterHub Spawner for LXD
Home-page: http://github.com/axw/jupyterhub-lxd-spawner
Author: Andrew Wilkins
Author-email: axwalk@gmail.com
License: MIT
Platform: UNKNOWN
Classifier: Framework :: IPython
Classifier: Intended Audience :: Developers
Classifier: Intended Audience :: Science/Research
Classifier: Programming Language :: Python
Classifier: License :: OSI Approved :: MIT License
Classifier: Development Status :: 4 - Beta
Classifier: Topic :: System :: Distributed Computing
